cidc_ngs_pipeline_api/__init__.py
cidc_ngs_pipeline_api/output_API.schema.json
cidc_ngs_pipeline_api/__pycache__/__init__.cpython-39.pyc
cidc_ngs_pipeline_api/atacseq/atacseq.md
cidc_ngs_pipeline_api/atacseq/atacseq_output_API.json
cidc_ngs_pipeline_api/atacseq/imgs/atacseq.png
cidc_ngs_pipeline_api/rna/rna.md
cidc_ngs_pipeline_api/rna/rna_config.schema.json
cidc_ngs_pipeline_api/rna/rna_output_API.json
cidc_ngs_pipeline_api/rna/imgs/RIMA.png
cidc_ngs_pipeline_api/tcr/tcr.md
cidc_ngs_pipeline_api/tcr/imgs/TCRseq.png
cidc_ngs_pipeline_api/wes/wes.md
cidc_ngs_pipeline_api/wes/wes_config.schema.json
cidc_ngs_pipeline_api/wes/wes_output_API.json
cidc_ngs_pipeline_api/wes/wes_output_API.py
cidc_ngs_pipeline_api/wes/wes_tumor_only_output_API.json
cidc_ngs_pipeline_api/wes/imgs/wes.png
nci_cidc_ngs_pipeline_api-0.1.26.dist-info/METADATA
nci_cidc_ngs_pipeline_api-0.1.26.dist-info/WHEEL
nci_cidc_ngs_pipeline_api-0.1.26.dist-info/top_level.txt
nci_cidc_ngs_pipeline_api-0.1.26.dist-info/RECORD
