Metadata-Version: 2.1
Name: nci_cidc_ngs_pipeline_api
Version: 0.1.26
Summary: The NCI CIDC NGS Pipeline output APIs
Home-page: https://github.com/NCI-CIDC/cidc-ngs-pipeline-api
Author: NCI
Author-email: nci-cidc-tools-admin@mail.nih.gov
License: MIT license
Keywords: cidc_ngs_pipeline_api
Classifier: Development Status :: 2 - Pre-Alpha
Classifier: Intended Audience :: Developers
Classifier: License :: OSI Approved :: MIT License
Classifier: Natural Language :: English
Classifier: Programming Language :: Python :: 3.9
Requires-Python: >=3.9
Requires-Dist: jsonschema ==4.20.0
